datacula/__init__.py
datacula/convert.py
datacula/loader.py
datacula/mie.py
datacula/stats.py
datacula/lake/datalake.py
datacula/lake/datastream.py
datacula/lake/plot.py
datacula/lake/processer.py
datacula/live/client_file_sync.py
datacula/live/data_imports.py
datacula/live/file_sync.py
datacula/live/main_data_save.py
datacula/live/server.py
datacula/live/server_data.py
datacula/test/convert_test.py
datacula/test/loader_test.py
datacula/test/stats_test.py
datacula/test/test_data.py
datacula-0.0.0.post1.dist-info/WHEEL
datacula-0.0.0.post1.dist-info/METADATA
datacula-0.0.0.post1.dist-info/RECORD
