Metadata-Version: 2.1
Name: datacula
Version: 0.0.0.post1
Summary: a python package for atmospheric particle-gas data analysis and visualization
Keywords: atmospheric,particles,climate,aerosol,particulate,parcel,clouds,datacula
Author-email: ngam <ngam@users.noreply.github.com>, Gorkowski <Gorkowski@users.noreply.github.com>
Requires-Python: >=3.9
Classifier: Programming Language :: Python :: 3
Classifier: Programming Language :: Python :: 3 :: Only
Classifier: License :: OSI Approved :: MIT License
Classifier: Intended Audience :: Science/Research
Classifier: Topic :: Scientific/Engineering :: Atmospheric Science
Requires-Dist: matplotlib
Requires-Dist: numpy
Requires-Dist: scipy
Requires-Dist: ipython
Requires-Dist: tqdm
Requires-Dist: PyMieScatt
Requires-Dist: particula
Requires-Dist: scheduler
Requires-Dist: pylint
Requires-Dist: flake8
Requires-Dist: jupyter-book
Requires-Dist: ghp-import
Requires-Dist: ipykernel
Requires-Dist: pandas
Requires-Dist: pylint ; extra == "dev"
Requires-Dist: pytest ; extra == "dev"
Requires-Dist: autopep8 ; extra == "dev"
Requires-Dist: jupyterlab ; extra == "dev"
Requires-Dist: pytype ; extra == "dev"
Requires-Dist: typing ; extra == "dev"
Requires-Dist: build ; extra == "dev"
Project-URL: homepage, https://github.com/uncscode/datacula
Project-URL: repository, https://github.com/uncscode/datacula
Provides-Extra: dev
